{
  "openapi": "3.0.1",
  "info": {
    "title": "InfoHubApplication",
    "version": "1.0"
  },
  "paths": {
    "/api/v1/company": {
      "post": {
        "tags": [
          "Company"
        ],
        "requestBody": {
          "content": {
            "application/json": {
              "schema": {
                "$ref": "#/components/schemas/CompanyViewModel"
              }
            },
            "text/json": {
              "schema": {
                "$ref": "#/components/schemas/CompanyViewModel"
              }
            },
            "application/*+json": {
              "schema": {
                "$ref": "#/components/schemas/CompanyViewModel"
              }
            }
          }
        },
        "responses": {
          "200": {
            "description": "OK"
          }
        }
      },
      "get": {
        "tags": [
          "Company"
        ],
        "responses": {
          "200": {
            "description": "OK"
          }
        }
      }
    },
    "/api/v1/company/{id}": {
      "delete": {
        "tags": [
          "Company"
        ],
        "parameters": [
          {
            "name": "id",
            "in": "path",
            "required": true,
            "schema": {
              "type": "integer",
              "format": "int32"
            }
          }
        ],
        "responses": {
          "200": {
            "description": "OK"
          }
        }
      },
      "get": {
        "tags": [
          "Company"
        ],
        "parameters": [
          {
            "name": "id",
            "in": "path",
            "required": true,
            "schema": {
              "type": "integer",
              "format": "int32"
            }
          }
        ],
        "responses": {
          "200": {
            "description": "OK"
          }
        }
      }
    },
    "/api/v1/files/{groupId}": {
      "post": {
        "tags": [
          "File"
        ],
        "parameters": [
          {
            "name": "groupId",
            "in": "path",
            "required": true,
            "schema": {
              "type": "integer",
              "format": "int32"
            }
          }
        ],
        "requestBody": {
          "content": {
            "multipart/form-data": {
              "schema": {
                "type": "object",
                "properties": {
                  "file": {
                    "type": "string",
                    "format": "binary"
                  }
                }
              },
              "encoding": {
                "file": {
                  "style": "form"
                }
              }
            }
          }
        },
        "responses": {
          "200": {
            "description": "OK"
          }
        }
      },
      "get": {
        "tags": [
          "File"
        ],
        "parameters": [
          {
            "name": "groupId",
            "in": "path",
            "required": true,
            "schema": {
              "type": "integer",
              "format": "int32"
            }
          }
        ],
        "responses": {
          "200": {
            "description": "OK"
          }
        }
      }
    },
    "/api/v1/files/{groupId}/{fileName}": {
      "get": {
        "tags": [
          "File"
        ],
        "parameters": [
          {
            "name": "groupId",
            "in": "path",
            "required": true,
            "schema": {
              "type": "integer",
              "format": "int32"
            }
          },
          {
            "name": "fileName",
            "in": "path",
            "required": true,
            "schema": {
              "type": "string"
            }
          }
        ],
        "responses": {
          "200": {
            "description": "OK"
          }
        }
      },
      "delete": {
        "tags": [
          "File"
        ],
        "parameters": [
          {
            "name": "groupId",
            "in": "path",
            "required": true,
            "schema": {
              "type": "integer",
              "format": "int32"
            }
          },
          {
            "name": "fileName",
            "in": "path",
            "required": true,
            "schema": {
              "type": "string"
            }
          }
        ],
        "responses": {
          "200": {
            "description": "OK"
          }
        }
      }
    },
    "/api/v1/group": {
      "post": {
        "tags": [
          "Group"
        ],
        "requestBody": {
          "content": {
            "application/json": {
              "schema": {
                "$ref": "#/components/schemas/GroupViewModel"
              }
            },
            "text/json": {
              "schema": {
                "$ref": "#/components/schemas/GroupViewModel"
              }
            },
            "application/*+json": {
              "schema": {
                "$ref": "#/components/schemas/GroupViewModel"
              }
            }
          }
        },
        "responses": {
          "200": {
            "description": "OK"
          }
        }
      },
      "get": {
        "tags": [
          "Group"
        ],
        "responses": {
          "200": {
            "description": "OK"
          }
        }
      }
    },
    "/api/v1/group/{id}": {
      "delete": {
        "tags": [
          "Group"
        ],
        "parameters": [
          {
            "name": "id",
            "in": "path",
            "required": true,
            "schema": {
              "type": "integer",
              "format": "int32"
            }
          }
        ],
        "responses": {
          "200": {
            "description": "OK"
          }
        }
      },
      "get": {
        "tags": [
          "Group"
        ],
        "parameters": [
          {
            "name": "id",
            "in": "path",
            "required": true,
            "schema": {
              "type": "integer",
              "format": "int32"
            }
          }
        ],
        "responses": {
          "200": {
            "description": "OK"
          }
        }
      }
    },
    "/api/v1/group/my-groups": {
      "get": {
        "tags": [
          "Group"
        ],
        "responses": {
          "200": {
            "description": "OK"
          }
        }
      }
    },
    "/api/v1/login": {
      "post": {
        "tags": [
          "Login"
        ],
        "requestBody": {
          "content": {
            "application/json": {
              "schema": {
                "$ref": "#/components/schemas/LoginViewModel"
              }
            },
            "text/json": {
              "schema": {
                "$ref": "#/components/schemas/LoginViewModel"
              }
            },
            "application/*+json": {
              "schema": {
                "$ref": "#/components/schemas/LoginViewModel"
              }
            }
          }
        },
        "responses": {
          "200": {
            "description": "OK"
          }
        }
      }
    },
    "/api/v1/message": {
      "post": {
        "tags": [
          "Message"
        ],
        "requestBody": {
          "content": {
            "application/json": {
              "schema": {
                "$ref": "#/components/schemas/MessageViewModel"
              }
            },
            "text/json": {
              "schema": {
                "$ref": "#/components/schemas/MessageViewModel"
              }
            },
            "application/*+json": {
              "schema": {
                "$ref": "#/components/schemas/MessageViewModel"
              }
            }
          }
        },
        "responses": {
          "200": {
            "description": "OK"
          }
        }
      },
      "get": {
        "tags": [
          "Message"
        ],
        "responses": {
          "200": {
            "description": "OK"
          }
        }
      }
    },
    "/api/v1/message/{id}": {
      "delete": {
        "tags": [
          "Message"
        ],
        "parameters": [
          {
            "name": "id",
            "in": "path",
            "required": true,
            "schema": {
              "type": "integer",
              "format": "int32"
            }
          }
        ],
        "responses": {
          "200": {
            "description": "OK"
          }
        }
      }
    },
    "/api/v1/message/group/{groupId}": {
      "get": {
        "tags": [
          "Message"
        ],
        "parameters": [
          {
            "name": "groupId",
            "in": "path",
            "required": true,
            "schema": {
              "type": "integer",
              "format": "int32"
            }
          }
        ],
        "responses": {
          "200": {
            "description": "OK"
          }
        }
      }
    },
    "/api/v1/user": {
      "post": {
        "tags": [
          "User"
        ],
        "requestBody": {
          "content": {
            "application/json": {
              "schema": {
                "$ref": "#/components/schemas/UserViewModel"
              }
            },
            "text/json": {
              "schema": {
                "$ref": "#/components/schemas/UserViewModel"
              }
            },
            "application/*+json": {
              "schema": {
                "$ref": "#/components/schemas/UserViewModel"
              }
            }
          }
        },
        "responses": {
          "200": {
            "description": "OK"
          }
        }
      },
      "get": {
        "tags": [
          "User"
        ],
        "responses": {
          "200": {
            "description": "OK"
          }
        }
      }
    },
    "/api/v1/user/{id}": {
      "delete": {
        "tags": [
          "User"
        ],
        "parameters": [
          {
            "name": "id",
            "in": "path",
            "required": true,
            "schema": {
              "type": "integer",
              "format": "int32"
            }
          }
        ],
        "responses": {
          "200": {
            "description": "OK"
          }
        }
      },
      "get": {
        "tags": [
          "User"
        ],
        "parameters": [
          {
            "name": "id",
            "in": "path",
            "required": true,
            "schema": {
              "type": "integer",
              "format": "int32"
            }
          }
        ],
        "responses": {
          "200": {
            "description": "OK"
          }
        }
      }
    }
  },
  "components": {
    "schemas": {
      "CompanyViewModel": {
        "required": [
          "name"
        ],
        "type": "object",
        "properties": {
          "name": {
            "minLength": 1,
            "type": "string"
          }
        },
        "additionalProperties": false
      },
      "GroupViewModel": {
        "required": [
          "companyId",
          "identifierType",
          "identifierValue",
          "name"
        ],
        "type": "object",
        "properties": {
          "name": {
            "minLength": 1,
            "type": "string"
          },
          "companyId": {
            "type": "integer",
            "format": "int32"
          },
          "identifierType": {
            "minLength": 1,
            "type": "string"
          },
          "identifierValue": {
            "minLength": 1,
            "type": "string"
          }
        },
        "additionalProperties": false
      },
      "LoginViewModel": {
        "required": [
          "email",
          "password"
        ],
        "type": "object",
        "properties": {
          "email": {
            "minLength": 1,
            "type": "string",
            "format": "email"
          },
          "password": {
            "minLength": 1,
            "type": "string"
          }
        },
        "additionalProperties": false
      },
      "MessageViewModel": {
        "required": [
          "groupId",
          "messageCategory",
          "messageContent",
          "userId"
        ],
        "type": "object",
        "properties": {
          "groupId": {
            "type": "integer",
            "format": "int32"
          },
          "userId": {
            "type": "integer",
            "format": "int32"
          },
          "messageCategory": {
            "minLength": 1,
            "type": "string"
          },
          "messageContent": {
            "minLength": 1,
            "type": "string"
          }
        },
        "additionalProperties": false
      },
      "UserViewModel": {
        "required": [
          "companyId",
          "email",
          "name",
          "password",
          "role"
        ],
        "type": "object",
        "properties": {
          "name": {
            "minLength": 1,
            "type": "string"
          },
          "email": {
            "minLength": 1,
            "type": "string",
            "format": "email"
          },
          "password": {
            "minLength": 1,
            "type": "string"
          },
          "role": {
            "minLength": 1,
            "type": "string"
          },
          "companyId": {
            "type": "integer",
            "format": "int32"
          }
        },
        "additionalProperties": false
      }
    },
    "securitySchemes": {
      "Bearer": {
        "type": "apiKey",
        "name": "Authorization",
        "in": "header"
      }
    }
  },
  "security": [
    {
      "Bearer": [ ]
    }
  ]
}